artfight/__init__.py
artfight/client.py
artfight/error.py
artfight/http.py
artfight/object/__init__.py
artfight/object/abc.py
artfight/object/attack.py
artfight/object/character.py
artfight/object/user.py
artfight/parser.py
artfight/util.py
artfight_api-0.1.2.dist-info/METADATA
artfight_api-0.1.2.dist-info/WHEEL
artfight_api-0.1.2.dist-info/RECORD
