Metadata-Version: 2.1
Name: artfight-api
Version: 0.1.2
Summary: A module for retrieving data from artfight.net
Home-page: https://github.com/NimajnebEC/artfight-api
License: MIT
Author: NimajnebEC
Author-email: nimajnebec@users.noreply.github.com
Requires-Python: >=3.8.1,<4.0.0
Classifier: License :: OSI Approved :: MIT License
Classifier: Programming Language :: Python :: 3
Classifier: Programming Language :: Python :: 3.9
Classifier: Programming Language :: Python :: 3.10
Classifier: Programming Language :: Python :: 3.11
Classifier: Programming Language :: Python :: 3.12
Requires-Dist: aiohttp[speedups] (>=3.8.4,<4.0.0)
Requires-Dist: beautifulsoup4 (>=4.12.2,<5.0.0)
Project-URL: Repository, https://github.com/NimajnebEC/artfight-api
